tfa-0.4.0.dist-info/METADATA
tfa-0.4.0.dist-info/WHEEL
tfa-0.4.0.dist-info/entry_points.txt
tfa-0.4.0.dist-info/licenses/LICENSE
tfa/__init__.py
tfa/cli.py
tfa/storage.py
tfa-0.4.0.dist-info/RECORD
