Metadata-Version: 2.1
Name: tfa
Version: 0.4.0
Summary: A command-line tool for managing two-factor authentication (2FA) TOTP codes.
Author-Email: Adam Kelly <adam@cthulahoops.org>
License: MIT
Requires-Python: <4.0,>=3.10
Requires-Dist: pyotp<3.0.0,>=2.9.0
Requires-Dist: click<9.0.0,>=8.1.7
Requires-Dist: qrcode<8.0.0,>=7.4.2
Requires-Dist: sqlite-utils<4.0,>=3.38
